qlip_serve/common/NOTICE
qlip_serve/common/README-PyPI.md
qlip_serve/common/__init__.py
qlip_serve/common/licenses/Apache-2.0.txt
qlip_serve/common/model.py
qlip_serve/common/model_config/__init__.py
qlip_serve/common/model_config/common.py
qlip_serve/common/model_config/exceptions.py
qlip_serve/common/model_config/generator.py
qlip_serve/common/model_config/grpc/__init__.py
qlip_serve/common/model_config/grpc/model_config_pb2.py
qlip_serve/common/model_config/model_config.py
qlip_serve/common/model_config/parser.py
qlip_serve/common/model_config/tensor.py
qlip_serve/common/model_config/triton_model_config.py
qlip_serve/common/model_config/utils.py
qlip_serve/common/payload.py
qlip_serve/common/pyproject.toml
qlip_serve/common/signature.py
qlip_serve/common/utils.py
qlip_serve_common-0.1.17.dist-info/METADATA
qlip_serve_common-0.1.17.dist-info/NOTICE
qlip_serve_common-0.1.17.dist-info/WHEEL
qlip_serve_common-0.1.17.dist-info/RECORD
