Metadata-Version: 2.3
Name: qlip-serve-common
Version: 0.1.17
Summary: Common abstractions and utilities for qlip.serve.* libraries
License: BSD-3-Clause
Author: TheStage AI team
Author-email: hello@thestage.ai
Requires-Python: >=3.10
Classifier: License :: OSI Approved :: BSD License
Classifier: Programming Language :: Python :: 3
Classifier: Programming Language :: Python :: 3.10
Classifier: Programming Language :: Python :: 3.11
Classifier: Programming Language :: Python :: 3.12
Classifier: Programming Language :: Python :: 3.13
Requires-Dist: numpy (<2.0.0)
Requires-Dist: pillow (>=10.2.0)
Requires-Dist: protobuf (>=5.26.0)
